async_websocket_pool/__init__.py
async_websocket_pool/websocket.py
async_websocket_pool-0.2.0.dist-info/METADATA
async_websocket_pool-0.2.0.dist-info/WHEEL
async_websocket_pool-0.2.0.dist-info/licenses/LICENSE
async_websocket_pool-0.2.0.dist-info/RECORD
