Metadata-Version: 2.4
Name: async-websocket-pool
Version: 0.2.0
Summary: async-websocket-pool is a Python library that enables efficient creation and management of a pool of asynchronous WebSocket clients.
License: MIT
License-File: LICENSE
Author: mpol1t
Requires-Python: >=3.10,<4.0
Classifier: License :: OSI Approved :: MIT License
Classifier: Programming Language :: Python :: 3
Classifier: Programming Language :: Python :: 3.10
Classifier: Programming Language :: Python :: 3.11
Classifier: Programming Language :: Python :: 3.12
Classifier: Programming Language :: Python :: 3.13
Classifier: Programming Language :: Python :: 3.14
Requires-Dist: websockets (>=15.0.1,<16.0.0)
